sequali/__init__.py
sequali/__main__.py
sequali/_qc.pyd
sequali/_qc.pyi
sequali/_seqident.pyd
sequali/_seqident.pyi
sequali/_version.py
sequali/adapters.py
sequali/py.typed
sequali/report_modules.py
sequali/sequence_identification.py
sequali/util.py
sequali/adapters/adapter_list.tsv
sequali/contaminants/Illumina.fasta
sequali/contaminants/README
sequali/contaminants/UniVec.fasta
sequali/contaminants/common_human_repeats.fasta
sequali/contaminants/oxford_nanopore.fasta
sequali/contaminants/oxford_nanopore_barcodes.fasta
sequali/pygal.js/README.md
sequali/pygal.js/2.0.x/pygal-tooltips.js
sequali/pygal.js/2.0.x/pygal-tooltips.min.js
sequali/static/sequali_report.css
sequali/static/svg_to_download_link.js
sequali-1.0.2.dist-info/licenses/LICENSE
sequali-1.0.2.dist-info/METADATA
sequali-1.0.2.dist-info/WHEEL
sequali-1.0.2.dist-info/entry_points.txt
sequali-1.0.2.dist-info/top_level.txt
sequali-1.0.2.dist-info/RECORD
