Metadata-Version: 2.4
Name: sequali
Version: 1.0.2
Summary: Sequali is a QC tool that generates useful graphs for both short and long-read data.
Author-email: Ruben Vorderman <r.h.p.vorderman@lumc.nl>
License-Expression: AGPL-3.0-or-later
Project-URL: Documentation, https://sequali.readthedocs.io
Project-URL: Homepage, https://github.com/rhpvorderman/sequali
Project-URL: Issue tracker, https://github.com/rhpvorderman/sequali/issues
Keywords: FASTQ,sequencing quality,uBAM,QC,nanopore,illumina
Classifier: Programming Language :: Python :: 3 :: Only
Classifier: Programming Language :: Python :: 3
Classifier: Programming Language :: Python :: 3.10
Classifier: Programming Language :: Python :: 3.11
Classifier: Programming Language :: Python :: 3.12
Classifier: Programming Language :: Python :: 3.13
Classifier: Programming Language :: Python :: 3.14
Classifier: Development Status :: 5 - Production/Stable
Classifier: Topic :: Scientific/Engineering :: Bio-Informatics
Requires-Python: >=3.10
License-File: LICENSE
Requires-Dist: xopen>=2.0.0
Requires-Dist: pygal>=3.0.4
Requires-Dist: tqdm
Dynamic: license-file
